lseg_analytics/pricing/__init__.py
lseg_analytics/pricing/_feature_flags.py
lseg_analytics/pricing/helpers.py
lseg_analytics/pricing/py.typed
lseg_analytics/pricing/_basic_client/__init__.py
lseg_analytics/pricing/_basic_client/_client.py
lseg_analytics/pricing/_basic_client/_configuration.py
lseg_analytics/pricing/_basic_client/_model_base.py
lseg_analytics/pricing/_basic_client/_patch.py
lseg_analytics/pricing/_basic_client/_serialization.py
lseg_analytics/pricing/_basic_client/_types.py
lseg_analytics/pricing/_basic_client/_version.py
lseg_analytics/pricing/_basic_client/py.typed
lseg_analytics/pricing/_basic_client/aio/__init__.py
lseg_analytics/pricing/_basic_client/aio/_client.py
lseg_analytics/pricing/_basic_client/aio/_configuration.py
lseg_analytics/pricing/_basic_client/aio/_patch.py
lseg_analytics/pricing/_basic_client/aio/operations/__init__.py
lseg_analytics/pricing/_basic_client/aio/operations/_operations.py
lseg_analytics/pricing/_basic_client/aio/operations/_patch.py
lseg_analytics/pricing/_basic_client/models/__init__.py
lseg_analytics/pricing/_basic_client/models/_enums.py
lseg_analytics/pricing/_basic_client/models/_models.py
lseg_analytics/pricing/_basic_client/models/_patch.py
lseg_analytics/pricing/_basic_client/operations/__init__.py
lseg_analytics/pricing/_basic_client/operations/_operations.py
lseg_analytics/pricing/_basic_client/operations/_patch.py
lseg_analytics/pricing/_client/__init__.py
lseg_analytics/pricing/_client/client.py
lseg_analytics/pricing/common/__init__.py
lseg_analytics/pricing/delivery/__init__.py
lseg_analytics/pricing/delivery/_endpoint_request.py
lseg_analytics/pricing/delivery/_logger.py
lseg_analytics/pricing/instruments/__init__.py
lseg_analytics/pricing/instruments/bond/__init__.py
lseg_analytics/pricing/instruments/bond/_functions.py
lseg_analytics/pricing/instruments/bond/_logger.py
lseg_analytics/pricing/instruments/bond_future/__init__.py
lseg_analytics/pricing/instruments/bond_future/_functions.py
lseg_analytics_pricing-1.1.0.dist-info/licenses/LICENSE
lseg_analytics_pricing-1.1.0.dist-info/METADATA
lseg_analytics_pricing-1.1.0.dist-info/WHEEL
lseg_analytics_pricing-1.1.0.dist-info/top_level.txt
lseg_analytics_pricing-1.1.0.dist-info/RECORD
