Metadata-Version: 2.4
Name: lseg-analytics-pricing
Version: 1.1.0
Summary: LSEG Analytics LFA SDK for Python
Author-email: analyticssdk <analyticssdk@lseg.com>
Maintainer-email: analyticssdk <analyticssdk@lseg.com>
Requires-Python: >=3.8
License-File: LICENSE
Requires-Dist: corehttp==1.0.0b5
Requires-Dist: python-dotenv
Requires-Dist: requests
Requires-Dist: isodate<1.0.0,>=0.6.1
Requires-Dist: lseg-analytics-core<2.0.0,>=1.1.0
Requires-Dist: pandas
Dynamic: license-file
